{
	"song": {
		"speed": 2.9,
		"stage": "limo",
		"player1": "pico-car",
		"player2": "mom-car",
		"player3": null,
		"events": [
			[
				13125,
				[
					[
						"Add Camera Zoom",
						"",
						""
					]
				]
			],
			[
				24750,
				[
					[
						"Add Camera Zoom",
						"",
						""
					]
				]
			],
			[
				26250,
				[
					[
						"Add Camera Zoom",
						"",
						""
					]
				]
			],
			[
				27750,
				[
					[
						"Add Camera Zoom",
						"",
						""
					]
				]
			],
			[
				29250,
				[
					[
						"Add Camera Zoom",
						"",
						""
					]
				]
			],
			[
				30750,
				[
					[
						"Add Camera Zoom",
						"",
						""
					]
				]
			],
			[
				32250,
				[
					[
						"Add Camera Zoom",
						"",
						""
					]
				]
			],
			[
				33750,
				[
					[
						"Add Camera Zoom",
						"",
						""
					]
				]
			],
			[
				35250,
				[
					[
						"Add Camera Zoom",
						"",
						""
					]
				]
			],
			[
				36750,
				[
					[
						"Add Camera Zoom",
						"",
						""
					]
				]
			],
			[
				38250,
				[
					[
						"Add Camera Zoom",
						"",
						""
					]
				]
			],
			[
				39750,
				[
					[
						"Add Camera Zoom",
						"",
						""
					]
				]
			],
			[
				41250,
				[
					[
						"Add Camera Zoom",
						"",
						""
					]
				]
			],
			[
				42750,
				[
					[
						"Add Camera Zoom",
						"",
						""
					]
				]
			],
			[
				44250,
				[
					[
						"Add Camera Zoom",
						"",
						""
					]
				]
			],
			[
				45750,
				[
					[
						"Add Camera Zoom",
						"",
						""
					]
				]
			],
			[
				47250,
				[
					[
						"Add Camera Zoom",
						"",
						""
					]
				]
			],
			[
				54750,
				[
					[
						"Add Camera Zoom",
						"",
						""
					]
				]
			],
			[
				60750,
				[
					[
						"Add Camera Zoom",
						"",
						""
					]
				]
			],
			[
				62250,
				[
					[
						"Add Camera Zoom",
						"",
						""
					]
				]
			],
			[
				63750,
				[
					[
						"Add Camera Zoom",
						"",
						""
					]
				]
			],
			[
				65250,
				[
					[
						"Add Camera Zoom",
						"",
						""
					]
				]
			],
			[
				66750,
				[
					[
						"Add Camera Zoom",
						"",
						""
					]
				]
			],
			[
				68250,
				[
					[
						"Add Camera Zoom",
						"",
						""
					]
				]
			],
			[
				69750,
				[
					[
						"Add Camera Zoom",
						"",
						""
					]
				]
			],
			[
				71250,
				[
					[
						"Add Camera Zoom",
						"",
						""
					]
				]
			],
			[
				72750,
				[
					[
						"Add Camera Zoom",
						"",
						""
					]
				]
			],
			[
				74250,
				[
					[
						"Add Camera Zoom",
						"",
						""
					]
				]
			],
			[
				75750,
				[
					[
						"Add Camera Zoom",
						"",
						""
					]
				]
			],
			[
				77250,
				[
					[
						"Add Camera Zoom",
						"",
						""
					]
				]
			],
			[
				78750,
				[
					[
						"Add Camera Zoom",
						"",
						""
					]
				]
			],
			[
				80250,
				[
					[
						"Add Camera Zoom",
						"",
						""
					]
				]
			],
			[
				81750,
				[
					[
						"Add Camera Zoom",
						"",
						""
					]
				]
			],
			[
				83250,
				[
					[
						"Add Camera Zoom",
						"",
						""
					]
				]
			],
			[
				84750,
				[
					[
						"Add Camera Zoom",
						"",
						""
					]
				]
			],
			[
				86250,
				[
					[
						"Add Camera Zoom",
						"",
						""
					]
				]
			],
			[
				87750,
				[
					[
						"Add Camera Zoom",
						"",
						""
					]
				]
			],
			[
				89250,
				[
					[
						"Add Camera Zoom",
						"",
						""
					]
				]
			],
			[
				90750,
				[
					[
						"Add Camera Zoom",
						"",
						""
					]
				]
			],
			[
				92250,
				[
					[
						"Add Camera Zoom",
						"",
						""
					]
				]
			],
			[
				93750,
				[
					[
						"Add Camera Zoom",
						"",
						""
					]
				]
			],
			[
				95250,
				[
					[
						"Add Camera Zoom",
						"",
						""
					]
				]
			]
		],
		"notes": [],
		"splashSkin": "noteSplashesCustom",
		"validScore": false,
		"gfVersion": "speakers",
		"bpm": 160,
		"mania": 3,
		"arrowSkin": "NOTE_assets_Custom",
		"needsVoices": true,
		"song": "Parasite"
	}
}